falibrary/__init__.py
falibrary/config.py
falibrary/library.py
falibrary/route.py
falibrary/utils.py
falibrary/templates/redoc.html
falibrary/templates/swagger.html
falibrary-0.5.4.dist-info/METADATA
falibrary-0.5.4.dist-info/RECORD
falibrary-0.5.4.dist-info/WHEEL
falibrary-0.5.4.dist-info/entry_points.txt
falibrary-0.5.4.dist-info/top_level.txt
