Metadata-Version: 2.1
Name: falibrary
Version: 0.5.4
Summary: UNKNOWN
Home-page: https://github.com/kemingy/falibrary
Author: Keming Yang
Author-email: kemingy94@gmail.com
License: UNKNOWN
Platform: UNKNOWN
Classifier: Programming Language :: Python :: 3
Requires-Dist: falcon (>=2.0.0)
Requires-Dist: pydantic (>=1.2)
